telegram_bot_mcp/__init__.py
telegram_bot_mcp/__main__.py
telegram_bot_mcp/server.py
telegram_bot_mcp/telegram_bot/client.py
telegram_bot_mcp-0.1.2.dist-info/METADATA
telegram_bot_mcp-0.1.2.dist-info/WHEEL
telegram_bot_mcp-0.1.2.dist-info/entry_points.txt
telegram_bot_mcp-0.1.2.dist-info/licenses/LICENSE
telegram_bot_mcp-0.1.2.dist-info/RECORD
